AUTHORS.rst
CONTRIBUTING.rst
HISTORY.rst
LICENSE
MANIFEST.in
README.md
setup.cfg
setup.py
chat/__init__.py
chat/chat.py
chat/cli.py
le_chat.egg-info/PKG-INFO
le_chat.egg-info/SOURCES.txt
le_chat.egg-info/dependency_links.txt
le_chat.egg-info/entry_points.txt
le_chat.egg-info/not-zip-safe
le_chat.egg-info/requires.txt
le_chat.egg-info/top_level.txt
tests/__init__.py
tests/test_chat.py