Metadata-Version: 1.2
Name: le-chat
Version: 0.1.0
Summary: Data parallelism study for natural language processing.
Home-page: https://github.com/yngtodd/chat
Author: Todd Young
Author-email: youngmt1@ornl.gov
License: BSD license
Keywords: chat
Platform: UNKNOWN
Classifier: Development Status :: 2 - Pre-Alpha
Classifier: Intended Audience :: Developers
Classifier: License :: OSI Approved :: BSD License
Classifier: Natural Language :: English
Classifier: Programming Language :: Python :: 3.6
Classifier: Programming Language :: Python :: 3.7
Classifier: Programming Language :: Python :: 3.8
Requires-Python: >=3.5
